{
  "main": {
    "id": "206a5deaf2c2fa52",
    "type": "split",
    "children": [
      {
        "id": "5aa0b61879b76ff8",
        "type": "tabs",
        "children": [
          {
            "id": "829c03d9ca5e3dc5",
            "type": "leaf",
            "state": {
              "type": "markdown",
              "state": {
                "file": "JavaScript/240418_JavaScript03.md",
                "mode": "source",
                "source": false
              }
            }
          },
          {
            "id": "113dd8f7d7d27a1d",
            "type": "leaf",
            "state": {
              "type": "markdown",
              "state": {
                "file": "VueJS/240508_Vue06.md",
                "mode": "source",
                "source": false
              }
            }
          }
        ],
        "currentTab": 1
      }
    ],
    "direction": "vertical"
  },
  "left": {
    "id": "906bf037f8870a9e",
    "type": "split",
    "children": [
      {
        "id": "cf32f8eb100f9a5a",
        "type": "tabs",
        "children": [
          {
            "id": "a205587ad021bc96",
            "type": "leaf",
            "state": {
              "type": "file-explorer",
              "state": {
                "sortOrder": "alphabetical"
              }
            }
          },
          {
            "id": "3dbe02e92bd3f98c",
            "type": "leaf",
            "state": {
              "type": "search",
              "state": {
                "query": "find",
                "matchingCase": false,
                "explainSearch": false,
                "collapseAll": false,
                "extraContext": false,
                "sortOrder": "alphabetical"
              }
            }
          },
          {
            "id": "7836e749af2cb777",
            "type": "leaf",
            "state": {
              "type": "bookmarks",
              "state": {}
            }
          }
        ]
      }
    ],
    "direction": "horizontal",
    "width": 200
  },
  "right": {
    "id": "19ff07be22e323b9",
    "type": "split",
    "children": [
      {
        "id": "9089f5028861e50e",
        "type": "tabs",
        "children": [
          {
            "id": "b1d9d149045e7e3c",
            "type": "leaf",
            "state": {
              "type": "backlink",
              "state": {
                "file": "VueJS/240508_Vue06.md",
                "collapseAll": false,
                "extraContext": false,
                "sortOrder": "alphabetical",
                "showSearch": false,
                "searchQuery": "",
                "backlinkCollapsed": false,
                "unlinkedCollapsed": true
              }
            }
          },
          {
            "id": "f8a4291dc74c85a4",
            "type": "leaf",
            "state": {
              "type": "outgoing-link",
              "state": {
                "file": "VueJS/240508_Vue06.md",
                "linksCollapsed": false,
                "unlinkedCollapsed": true
              }
            }
          },
          {
            "id": "c090b29235749484",
            "type": "leaf",
            "state": {
              "type": "tag",
              "state": {
                "sortOrder": "frequency",
                "useHierarchy": true
              }
            }
          },
          {
            "id": "0c4e96e554eccfdb",
            "type": "leaf",
            "state": {
              "type": "outline",
              "state": {
                "file": "VueJS/240508_Vue06.md"
              }
            }
          }
        ],
        "currentTab": 3
      }
    ],
    "direction": "horizontal",
    "width": 300,
    "collapsed": true
  },
  "left-ribbon": {
    "hiddenItems": {
      "switcher:Open quick switcher": false,
      "graph:Open graph view": false,
      "canvas:Create new canvas": false,
      "daily-notes:Open today's daily note": false,
      "templates:Insert template": false,
      "command-palette:Open command palette": false
    }
  },
  "active": "113dd8f7d7d27a1d",
  "lastOpenFiles": [
    "VueJS/240507_Vue05.md",
    "JavaScript/240418_JavaScript03.md",
    "VueJS/240508_Vue06.md",
    "daily/2024-01-18.md",
    "img/240508_20.PNG",
    "img/240508_19.PNG",
    "img/240508_18.PNG",
    "img/240508_17.PNG",
    "img/240508_16.PNG",
    "img/240508_15.PNG",
    "img/240508_14.PNG",
    "img/240508_13.PNG",
    "img/240508_12.PNG",
    "img/240508_11.PNG",
    "VueJS/240425_Vue01.md",
    "React/BASIC07_Practice_Movie_APP.md",
    "React/BASIC06_EFFECTS.md"
  ]
}